odoo10_addon_membership_prorrate_variable_period-10.0.1.0.0-py2.7-nspkg.pth
odoo/addons/membership_prorrate_variable_period/README.rst
odoo/addons/membership_prorrate_variable_period/__init__.py
odoo/addons/membership_prorrate_variable_period/__manifest__.py
odoo/addons/membership_prorrate_variable_period/i18n/ca.po
odoo/addons/membership_prorrate_variable_period/i18n/de.po
odoo/addons/membership_prorrate_variable_period/i18n/es.po
odoo/addons/membership_prorrate_variable_period/i18n/es_MX.po
odoo/addons/membership_prorrate_variable_period/i18n/fi.po
odoo/addons/membership_prorrate_variable_period/i18n/fr.po
odoo/addons/membership_prorrate_variable_period/i18n/fr_CH.po
odoo/addons/membership_prorrate_variable_period/i18n/hr.po
odoo/addons/membership_prorrate_variable_period/i18n/hr_HR.po
odoo/addons/membership_prorrate_variable_period/i18n/it.po
odoo/addons/membership_prorrate_variable_period/i18n/pt_BR.po
odoo/addons/membership_prorrate_variable_period/i18n/pt_PT.po
odoo/addons/membership_prorrate_variable_period/i18n/ro.po
odoo/addons/membership_prorrate_variable_period/i18n/sl.po
odoo/addons/membership_prorrate_variable_period/i18n/tr.po
odoo/addons/membership_prorrate_variable_period/i18n/tr_TR.po
odoo/addons/membership_prorrate_variable_period/i18n/vi_VN.po
odoo/addons/membership_prorrate_variable_period/i18n/zh_CN.po
odoo/addons/membership_prorrate_variable_period/models/__init__.py
odoo/addons/membership_prorrate_variable_period/models/account_invoice.py
odoo/addons/membership_prorrate_variable_period/models/product_template.py
odoo/addons/membership_prorrate_variable_period/static/description/icon.png
odoo/addons/membership_prorrate_variable_period/static/description/icon.svg
odoo/addons/membership_prorrate_variable_period/tests/__init__.py
odoo/addons/membership_prorrate_variable_period/tests/test_membership_prorrate_variable_period.py
odoo10_addon_membership_prorrate_variable_period-10.0.1.0.0.dist-info/DESCRIPTION.rst
odoo10_addon_membership_prorrate_variable_period-10.0.1.0.0.dist-info/METADATA
odoo10_addon_membership_prorrate_variable_period-10.0.1.0.0.dist-info/RECORD
odoo10_addon_membership_prorrate_variable_period-10.0.1.0.0.dist-info/WHEEL
odoo10_addon_membership_prorrate_variable_period-10.0.1.0.0.dist-info/metadata.json
odoo10_addon_membership_prorrate_variable_period-10.0.1.0.0.dist-info/namespace_packages.txt
odoo10_addon_membership_prorrate_variable_period-10.0.1.0.0.dist-info/top_level.txt
